{
  "_type": "export",
  "__export_format": 4,
  "__export_date": "2024-01-01T00:00:00.000Z",
  "__export_source": "insomnia.desktop.app:v2023.5.8",
  "resources": [
    {
      "_id": "req_root",
      "parentId": "wrk_pdf_api",
      "modified": 1704067200000,
      "created": 1704067200000,
      "url": "{{ _.base_url }}/",
      "name": "GET / - Status da API",
      "description": "Endpoint raiz para verificar o status da API",
      "method": "GET",
      "body": {},
      "parameters": [],
      "headers": [],
      "authentication": {},
      "metaSortKey": -1704067200000,
      "isPrivate": false,
      "settingStoreCookies": true,
      "settingSendCookies": true,
      "settingDisableRenderRequestBody": false,
      "settingEncodeUrl": true,
      "settingRebuildPath": true,
      "settingFollowRedirects": "global",
      "_type": "request"
    },
    {
      "_id": "req_health",
      "parentId": "wrk_pdf_api",
      "modified": 1704067200000,
      "created": 1704067200000,
      "url": "{{ _.base_url }}/health",
      "name": "GET /health - Health Check",
      "description": "Endpoint para verificação de saúde da aplicação",
      "method": "GET",
      "body": {},
      "parameters": [],
      "headers": [],
      "authentication": {},
      "metaSortKey": -1704067200000,
      "isPrivate": false,
      "settingStoreCookies": true,
      "settingSendCookies": true,
      "settingDisableRenderRequestBody": false,
      "settingEncodeUrl": true,
      "settingRebuildPath": true,
      "settingFollowRedirects": "global",
      "_type": "request"
    },
    {
      "_id": "req_convert",
      "parentId": "wrk_pdf_api",
      "modified": 1704067200000,
      "created": 1704067200000,
      "url": "{{ _.base_url }}/convert-pdf",
      "name": "POST /convert-pdf - Converter PDF",
      "description": "Endpoint para converter PDF em Markdown",
      "method": "POST",
      "body": {
        "mimeType": "multipart/form-data",
        "params": [
          {
            "name": "file",
            "value": "",
            "type": "file",
            "fileName": "",
            "description": "Arquivo PDF para converter"
          }
        ]
      },
      "parameters": [],
      "headers": [],
      "authentication": {},
      "metaSortKey": -1704067200000,
      "isPrivate": false,
      "settingStoreCookies": true,
      "settingSendCookies": true,
      "settingDisableRenderRequestBody": false,
      "settingEncodeUrl": true,
      "settingRebuildPath": true,
      "settingFollowRedirects": "global",
      "_type": "request"
    },
    {
      "_id": "wrk_pdf_api",
      "parentId": null,
      "modified": 1704067200000,
      "created": 1704067200000,
      "name": "PDF to Markdown API",
      "description": "API para converter PDFs em Markdown",
      "scope": "collection",
      "_type": "workspace"
    },
    {
      "_id": "env_local",
      "parentId": "wrk_pdf_api",
      "modified": 1704067200000,
      "created": 1704067200000,
      "name": "Local Environment",
      "data": {
        "base_url": "http://localhost:8000"
      },
      "dataPropertyOrder": {
        "&": [
          "base_url"
        ]
      },
      "color": null,
      "isPrivate": false,
      "metaSortKey": 1704067200000,
      "_type": "environment"
    }
  ]
}

